[{
  "_id": {
    "$oid": "63aa479bf71059c8b82ead76"
  },
  "MedicineName": "Madopar",
  "MedicineDose": 1,
  "IsComplete": true,
  "Time": 1,
  "Days": [
    2,
    3
  ],
  "OwnerID": "2021dbdb-c00a-4de2-bbdd-6f6d1cd5d6e6"
},{
  "_id": {
    "$oid": "63beb7e0280d5384772a4d78"
  },
  "MedicineName": "Öksürük şurubu",
  "MedicineDose": 1,
  "IsComplete": false,
  "Time": 2,
  "Days": [
    3,
    4,
    5
  ],
  "OwnerID": "8e7e9112-3a1f-4991-b398-767dd318b61b"
},{
  "_id": {
    "$oid": "63bebbf9a47246c05ac1b98d"
  },
  "MedicineName": "Aspirin",
  "MedicineDose": 2,
  "IsComplete": true,
  "Time": 4,
  "Days": [
    5,
    6
  ],
  "OwnerID": "8e7e9112-3a1f-4991-b398-767dd318b61b"
},{
  "_id": {
    "$oid": "63beccb09804ecbb3f30a7a4"
  },
  "MedicineName": "Theraflu",
  "MedicineDose": 4,
  "IsComplete": true,
  "Time": 4,
  "Days": [
    2,
    3
  ],
  "OwnerID": "2021dbdb-c00a-4de2-bbdd-6f6d1cd5d6e6"
},{
  "_id": {
    "$oid": "63beccd29804ecbb3f30a7a5"
  },
  "MedicineName": "Otrivine",
  "MedicineDose": 2,
  "IsComplete": true,
  "Time": 12,
  "Days": [
    0,
    2,
    4,
    6
  ],
  "OwnerID": "2021dbdb-c00a-4de2-bbdd-6f6d1cd5d6e6"
}]